go_v_tanki/__init__.py
go_v_tanki/bot.py
go_v_tanki-0.1.0.dist-info/METADATA
go_v_tanki-0.1.0.dist-info/WHEEL
go_v_tanki-0.1.0.dist-info/licenses/LICENSE
go_v_tanki-0.1.0.dist-info/RECORD
